basilica/__init__.py
basilica/_basilica.abi3.so
basilica/_basilica.pyi
basilica/_deployment.py
basilica/decorators.py
basilica/exceptions.py
basilica/source.py
basilica/spec.py
basilica/templates/__init__.py
basilica/templates/model_size.py
basilica/volume.py
basilica_sdk-0.15.0.dist-info/METADATA
basilica_sdk-0.15.0.dist-info/WHEEL
basilica_sdk-0.15.0.dist-info/RECORD
