Metadata-Version: 2.4
Name: basilica-sdk
Version: 0.15.0
Classifier: Development Status :: 4 - Beta
Classifier: Intended Audience :: Developers
Classifier: Intended Audience :: Science/Research
Classifier: License :: OSI Approved :: MIT License
Classifier: License :: OSI Approved :: Apache Software License
Classifier: Operating System :: OS Independent
Classifier: Programming Language :: Rust
Classifier: Programming Language :: Python :: Implementation :: CPython
Classifier: Programming Language :: Python :: 3
Classifier: Programming Language :: Python :: 3.10
Classifier: Programming Language :: Python :: 3.11
Classifier: Programming Language :: Python :: 3.12
Classifier: Programming Language :: Python :: 3.13
Classifier: Topic :: Scientific/Engineering :: Artificial Intelligence
Classifier: Topic :: Software Development :: Libraries :: Python Modules
Classifier: Topic :: System :: Distributed Computing
Classifier: Typing :: Typed
Requires-Dist: pytest>=7.0 ; extra == 'dev'
Requires-Dist: pytest-asyncio>=0.21 ; extra == 'dev'
Requires-Dist: mypy>=1.0 ; extra == 'dev'
Requires-Dist: maturin>=1.0 ; extra == 'dev'
Provides-Extra: dev
Summary: Python SDK for deploying containerized applications on the Basilica GPU cloud
Keywords: gpu,cloud,deployment,basilica,compute,kubernetes,ml,ai,machine-learning,deep-learning
Author-email: Basilica Team <team@basilica.ai>
License: MIT OR Apache-2.0
Requires-Python: >=3.10
Project-URL: Changelog, https://github.com/one-covenant/basilica/blob/main/crates/basilica-sdk-python/CHANGELOG.md
Project-URL: Documentation, https://docs.basilica.ai
Project-URL: Homepage, https://basilica.ai
Project-URL: Issues, https://github.com/one-covenant/basilica/issues
Project-URL: Repository, https://github.com/one-covenant/basilica
